test/delay.v
module delay 
	#(parameter length=10)
	(
	input in1,
	input in2,
	output reg out
	);

	reg [9:0] inter;
	genvar i;

	always @(in1, in2) begin
		#5 inter[0] = in1 & in2;
	end

	generate
		for (i=1; i < length; i = i + 1) begin
			always @(inter[i-1], in2) begin
				#5 inter[i] = inter[i-1] & in2;
			end
		end
	endgenerate

	always @(inter[length-1], in2) begin
		#5 out = inter[length-1] & in2;
	end

	initial begin
		inter = 0;
		out = 0;
	end

endmodule

test/block.v
module block(
	input trigger,
	input done,
	output control
	);

	reg control;
	reg planB;
	wire planBreset;

	delay d(
		.in1(planB),
		.in2(~done),
		.out(planBreset)
		);

	always @(posedge trigger or posedge planBreset or negedge done) begin
		#1 control <= 1;
		#2 planB <= 0;
	end

	always @(posedge control) begin
		#6 control <= 0;
	end

	always @(negedge control) begin
		#2 planB <= 1;
	end

	initial begin
		control = 0;
		planB = 0;
	end

endmodule

test/test_tb.v
`timescale 1ns/1ns

module test_tb();

	reg trigger;
	reg done;
	wire ctrl;

	// Functional
	block b(
		.trigger(trigger),
		.done(done),
		.control(ctrl)
		);

	initial begin
		$dumpfile("test_tb.vcd");
		$dumpvars(0, test_tb);
		trigger = 0;
		done = 1;
		#100
		done = 0;
		#80
		done = 1;
		#6
		done = 0;
		#300

		$finish;
	end

endmodule

test/test_tb.vcd
$date
	Mon Dec 14 16:22:54 2020
$end
$version
	Icarus Verilog
$end
$timescale
	1ns
$end
$scope module test_tb $end
$var wire 1 ! ctrl $end
$var reg 1 " done $end
$var reg 1 # trigger $end
$scope module b $end
$var wire 1 " done $end
$var wire 1 # trigger $end
$var wire 1 $ planBreset $end
$var reg 1 ! control $end
$var reg 1 % planB $end
$scope module d $end
$var wire 1 % in1 $end
$var wire 1 & in2 $end
$var reg 10 ' inter [9:0] $end
$var reg 1 $ out $end
$scope begin genblk1[1] $end
$upscope $end
$scope begin genblk1[2] $end
$upscope $end
$scope begin genblk1[3] $end
$upscope $end
$scope begin genblk1[4] $end
$upscope $end
$scope begin genblk1[5] $end
$upscope $end
$scope begin genblk1[6] $end
$upscope $end
$scope begin genblk1[7] $end
$upscope $end
$scope begin genblk1[8] $end
$upscope $end
$scope begin genblk1[9] $end
$upscope $end
$upscope $end
$upscope $end
$upscope $end
$enddefinitions $end
#0
$dumpvars
b0 '
0&
0%
0$
0#
1"
0!
$end
#2
1%
#100
1&
0"
#101
1!
#103
0%
#107
0!
#109
1%
#114
b1 '
#119
b11 '
#124
b111 '
#129
b1111 '
#134
b11111 '
#139
b111111 '
#144
b1111111 '
#149
b11111111 '
#154
b111111111 '
#159
b1111111111 '
#164
1$
#165
1!
#167
0%
#171
0!
#172
b1111111110 '
#173
1%
#177
b1111111100 '
#178
b1111111101 '
#180
0&
1"
#182
b1111111001 '
#185
0$
b0 '
#186
1&
0"
#187
1!
#189
0%
#193
0!
#195
1%
#200
b1 '
#205
b11 '
#210
b111 '
#215
b1111 '
#220
b11111 '
#225
b111111 '
#230
b1111111 '
#235
b11111111 '
#240
b111111111 '
#245
b1111111111 '
#250
1$
#251
1!
#253
0%
#257
0!
#258
b1111111110 '
#259
1%
#263
b1111111100 '
#264
b1111111101 '
#268
b1111111001 '
#269
b1111111011 '
#273
b1111110011 '
#274
b1111110111 '
#278
b1111100111 '
#279
b1111101111 '
#283
b1111001111 '
#284
b1111011111 '
#288
b1110011111 '
#289
b1110111111 '
#293
b1100111111 '
#294
b1101111111 '
#298
b1001111111 '
#299
b1011111111 '
#303
b11111111 '
#304
b111111111 '
#308
0$
#309
b1111111111 '
#314
1$
#315
1!
#317
0%
#321
0!
#322
b1111111110 '
#323
1%
#327
b1111111100 '
#328
b1111111101 '
#332
b1111111001 '
#333
b1111111011 '
#337
b1111110011 '
#338
b1111110111 '
#342
b1111100111 '
#343
b1111101111 '
#347
b1111001111 '
#348
b1111011111 '
#352
b1110011111 '
#353
b1110111111 '
#357
b1100111111 '
#358
b1101111111 '
#362
b1001111111 '
#363
b1011111111 '
#367
b11111111 '
#368
b111111111 '
#372
0$
#373
b1111111111 '
#378
1$
#379
1!
#381
0%
#385
0!
#386
b1111111110 '
#387
1%
#391
b1111111100 '
#392
b1111111101 '
#396
b1111111001 '
#397
b1111111011 '
#401
b1111110011 '
#402
b1111110111 '
#406
b1111100111 '
#407
b1111101111 '
#411
b1111001111 '
#412
b1111011111 '
#416
b1110011111 '
#417
b1110111111 '
#421
b1100111111 '
#422
b1101111111 '
#426
b1001111111 '
#427
b1011111111 '
#431
b11111111 '
#432
b111111111 '
#436
0$
#437
b1111111111 '
#442
1$
#443
1!
#445
0%
#449
0!
#450
b1111111110 '
#451
1%
#455
b1111111100 '
#456
b1111111101 '
#460
b1111111001 '
#461
b1111111011 '
#465
b1111110011 '
#466
b1111110111 '
#470
b1111100111 '
#471
b1111101111 '
#475
b1111001111 '
#476
b1111011111 '
#480
b1110011111 '
#481
b1110111111 '
#485
b1100111111 '
#486
b1101111111 '
